pystrands/__init__.py
pystrands/__main__.py
pystrands/client.py
pystrands/context.py
pystrands-0.1.2.dist-info/METADATA
pystrands-0.1.2.dist-info/WHEEL
pystrands-0.1.2.dist-info/top_level.txt
pystrands-0.1.2.dist-info/RECORD
