Metadata-Version: 2.4
Name: pystrands
Version: 0.1.2
Summary: A lightweight, framework-agnostic real-time library for Python applications.
Author-email: Diwakar <diwakarrankawat@gmail.com>
License: MIT
Project-URL: Homepage, https://github.com/pystrands/pystrands
Project-URL: Documentation, https://github.com/pystrands/pystrands#readme
Project-URL: Bug Tracker, https://github.com/pystrands/pystrands/issues
Keywords: websocket,realtime,tcp,server,client,messaging
Classifier: Development Status :: 4 - Beta
Classifier: Intended Audience :: Developers
Classifier: License :: OSI Approved :: MIT License
Classifier: Programming Language :: Python :: 3
Classifier: Programming Language :: Python :: 3.8
Classifier: Programming Language :: Python :: 3.9
Classifier: Programming Language :: Python :: 3.10
Classifier: Programming Language :: Python :: 3.11
Classifier: Topic :: Software Development :: Libraries :: Python Modules
Classifier: Topic :: Internet :: WWW/HTTP
Classifier: Operating System :: OS Independent
Requires-Python: >=3.8
